jupyterlite_server_contents/__init__.py
jupyterlite_server_contents/_version.py
jupyterlite_server_contents-0.1.1.data/data/share/jupyter/labextensions/jupyterlite-server-contents/package.json
jupyterlite_server_contents-0.1.1.data/data/share/jupyter/labextensions/jupyterlite-server-contents/static/509.4b0d25595cc2efc5db38.js
jupyterlite_server_contents-0.1.1.data/data/share/jupyter/labextensions/jupyterlite-server-contents/static/728.9bc006b4e7fd08682e1a.js
jupyterlite_server_contents-0.1.1.data/data/share/jupyter/labextensions/jupyterlite-server-contents/static/remoteEntry.495fd967aeb55ededfa1.js
jupyterlite_server_contents-0.1.1.data/data/share/jupyter/labextensions/jupyterlite-server-contents/static/style.js
jupyterlite_server_contents-0.1.1.data/data/share/jupyter/labextensions/jupyterlite-server-contents/static/third-party-licenses.json
jupyterlite_server_contents-0.1.1.data/data/share/jupyter/labextensions/jupyterlite-server-contents/install.json
jupyterlite_server_contents-0.1.1.dist-info/METADATA
jupyterlite_server_contents-0.1.1.dist-info/WHEEL
jupyterlite_server_contents-0.1.1.dist-info/licenses/LICENSE
jupyterlite_server_contents-0.1.1.dist-info/RECORD
