Metadata-Version: 2.4
Name: jupyterlite_server_contents
Version: 0.1.1
Summary: Access server contents from JupyterLite
Project-URL: Homepage, https://github.com/jtpio/jupyterlite-server-contents
Project-URL: Bug Tracker, https://github.com/jtpio/jupyterlite-server-contents/issues
Project-URL: Repository, https://github.com/jtpio/jupyterlite-server-contents.git
Author: Jeremy Tuloup
License: BSD 3-Clause License
License-File: LICENSE
Keywords: jupyter,jupyterlab,jupyterlab-extension
Classifier: Framework :: Jupyter
Classifier: Framework :: Jupyter :: JupyterLab
Classifier: Framework :: Jupyter :: JupyterLab :: 4
Classifier: Framework :: Jupyter :: JupyterLab :: Extensions
Classifier: Framework :: Jupyter :: JupyterLab :: Extensions :: Prebuilt
Classifier: License :: OSI Approved :: BSD License
Classifier: Programming Language :: Python
Classifier: Programming Language :: Python :: 3
Classifier: Programming Language :: Python :: 3.10
Classifier: Programming Language :: Python :: 3.11
Classifier: Programming Language :: Python :: 3.12
Classifier: Programming Language :: Python :: 3.13
Classifier: Programming Language :: Python :: 3.14
Requires-Python: >=3.10
Provides-Extra: dev
Requires-Dist: jupyterlite-core>=0.7.0; extra == 'dev'
Requires-Dist: jupyterlite-pyodide-kernel>=0.7.0; extra == 'dev'
